twscrape/__init__.py
twscrape/account.py
twscrape/accounts_pool.py
twscrape/api.py
twscrape/cli.py
twscrape/db.py
twscrape/imap.py
twscrape/logger.py
twscrape/login.py
twscrape/models.py
twscrape/queue_client.py
twscrape/utils.py
twscrape/xclid.py
twscrape680-0.19.7.dist-info/METADATA
twscrape680-0.19.7.dist-info/WHEEL
twscrape680-0.19.7.dist-info/entry_points.txt
twscrape680-0.19.7.dist-info/licenses/LICENSE
twscrape680-0.19.7.dist-info/RECORD
