Metadata-Version: 2.4
Name: twscrape680
Version: 0.19.7
Summary:  
Author-email: xx <x@x.x>
License: MIT
License-File: LICENSE
Requires-Python: >=3.10
Requires-Dist: aiosqlite>=0.17.0
Requires-Dist: beautifulsoup4>=4.13.0
Requires-Dist: fake-useragent>=1.4.0
Requires-Dist: httpx>=0.26.0
Requires-Dist: loguru>=0.7.0
Requires-Dist: pyotp>=2.9.0
Provides-Extra: dev
Requires-Dist: build>=1.2.2; extra == 'dev'
Requires-Dist: pyright>=1.1.369; extra == 'dev'
Requires-Dist: pytest-asyncio>=0.23.3; extra == 'dev'
Requires-Dist: pytest-cov>=4.1.0; extra == 'dev'
Requires-Dist: pytest-httpx>=0.28.0; extra == 'dev'
Requires-Dist: pytest>=7.4.4; extra == 'dev'
Requires-Dist: ruff>=0.1.11; extra == 'dev'
